{
  "version": "7",
  "dialect": "sqlite",
  "entries": [
    {
      "idx": 0,
      "version": "6",
      "when": 1784211397282,
      "tag": "0000_amusing_the_hood",
      "breakpoints": true
    },
    {
      "idx": 1,
      "version": "6",
      "when": 1784213109789,
      "tag": "0001_sharp_toro",
      "breakpoints": true
    },
    {
      "idx": 2,
      "version": "6",
      "when": 1784213856002,
      "tag": "0002_bumpy_hardball",
      "breakpoints": true
    },
    {
      "idx": 3,
      "version": "6",
      "when": 1784213952572,
      "tag": "0003_lucky_karen_page",
      "breakpoints": true
    },
    {
      "idx": 4,
      "version": "6",
      "when": 1784216473100,
      "tag": "0004_silky_titania",
      "breakpoints": true
    },
    {
      "idx": 5,
      "version": "6",
      "when": 1784217948478,
      "tag": "0005_special_sugar_man",
      "breakpoints": true
    },
    {
      "idx": 6,
      "version": "6",
      "when": 1784218701612,
      "tag": "0006_known_gabe_jones",
      "breakpoints": true
    },
    {
      "idx": 7,
      "version": "6",
      "when": 1784224671595,
      "tag": "0007_bizarre_luke_cage",
      "breakpoints": true
    },
    {
      "idx": 8,
      "version": "6",
      "when": 1784226120054,
      "tag": "0008_breezy_trauma",
      "breakpoints": true
    },
    {
      "idx": 9,
      "version": "6",
      "when": 1784226511495,
      "tag": "0009_easy_secret_warriors",
      "breakpoints": true
    },
    {
      "idx": 10,
      "version": "6",
      "when": 1784232781903,
      "tag": "0010_sticky_mephisto",
      "breakpoints": true
    },
    {
      "idx": 11,
      "version": "6",
      "when": 1784233169389,
      "tag": "0011_robust_adam_destine",
      "breakpoints": true
    },
    {
      "idx": 12,
      "version": "6",
      "when": 1784234076650,
      "tag": "0012_fearless_major_mapleleaf",
      "breakpoints": true
    },
    {
      "idx": 13,
      "version": "6",
      "when": 1784238816697,
      "tag": "0013_great_silver_sable",
      "breakpoints": true
    },
    {
      "idx": 14,
      "version": "6",
      "when": 1784239951611,
      "tag": "0014_careless_master_chief",
      "breakpoints": true
    },
    {
      "idx": 15,
      "version": "6",
      "when": 1784668143401,
      "tag": "0015_free_omega_sentinel",
      "breakpoints": true
    }
  ]
}